MatrixPy/__init__.py
MatrixPy/gen_matrix.py
MatrixPy/matrix.py
MatrixPy/print_matrix.py
MatrixPy/operations/__init__.py
MatrixPy/operations/add.py
MatrixPy/operations/det.py
MatrixPy/operations/eqs_system.py
MatrixPy/operations/inv.py
MatrixPy/operations/mult.py
MatrixPy/operations/sub.py
MatrixPy/operations/transpose.py
MatrixPy-1.2.3b3.dist-info/LICENSE.txt
MatrixPy-1.2.3b3.dist-info/METADATA
MatrixPy-1.2.3b3.dist-info/RECORD
MatrixPy-1.2.3b3.dist-info/WHEEL
MatrixPy-1.2.3b3.dist-info/top_level.txt
