Metadata-Version: 2.1
Name: MatrixPy
Version: 1.2.3b3
Summary: A simple handler for matrix objects.
Home-page: https://github.com/shaybrynes/MatrixPy
Author: Shay Brynes
Author-email: shay.brynes@hotmail.co.uk
License: UNKNOWN
Keywords: maths matrix matrices
Platform: UNKNOWN
Classifier: Development Status :: 4 - Beta
Classifier: Intended Audience :: Developers
Classifier: Topic :: Scientific/Engineering :: Mathematics
Classifier: License :: OSI Approved :: Apache 2.0
Classifier: Programming Language :: Python :: 3
Classifier: Programming Language :: Python :: 3.3
Classifier: Programming Language :: Python :: 3.4
Classifier: Programming Language :: Python :: 3.5
Classifier: Programming Language :: Python :: 3.6
